switcore/__init__.py
switcore/async_httpclient.py
switcore/constants.py
switcore/httpclient.py
switcore/logger.py
switcore/py.typed
switcore/pydantic_base_model.py
switcore/type.py
switcore/action/__init__.py
switcore/action/activity_handler_abc.py
switcore/action/activity_router.py
switcore/action/async_activity_handler_abc.py
switcore/action/base_activity_handler.py
switcore/action/dependencies.py
switcore/action/exceptions.py
switcore/action/schemas.py
switcore/api/__init__.py
switcore/api/helpers.py
switcore/api/channel/__init__.py
switcore/api/channel/async_service.py
switcore/api/channel/schemas.py
switcore/api/channel/service.py
switcore/api/message/__init__.py
switcore/api/message/service.py
switcore/api/user/__init__.py
switcore/api/user/schemas.py
switcore/api/user/service.py
switcore/api/workspace/__init__.py
switcore/api/workspace/async_service.py
switcore/api/workspace/schemas.py
switcore/api/workspace/service.py
switcore/auth/__init__.py
switcore/auth/async_repository.py
switcore/auth/constants.py
switcore/auth/dependencies.py
switcore/auth/exception.py
switcore/auth/models.py
switcore/auth/oauth2.py
switcore/auth/repository.py
switcore/auth/router.py
switcore/auth/schemas.py
switcore/auth/signature_verification.py
switcore/auth/utils.py
switcore/ui/Icon.py
switcore/ui/__init__.py
switcore/ui/button.py
switcore/ui/collection_entry.py
switcore/ui/container.py
switcore/ui/datepicker.py
switcore/ui/divider.py
switcore/ui/element_components.py
switcore/ui/file.py
switcore/ui/header.py
switcore/ui/html_frame.py
switcore/ui/image.py
switcore/ui/image_grid.py
switcore/ui/info_card.py
switcore/ui/input.py
switcore/ui/interactive_image.py
switcore/ui/item.py
switcore/ui/search.py
switcore/ui/select.py
switcore/ui/select_item.py
switcore/ui/signIn_page.py
switcore/ui/tabs.py
switcore/ui/text_paragraph.py
switcore/ui/textarea.py
swit_core-100.0.3.dist-info/METADATA
swit_core-100.0.3.dist-info/WHEEL
swit_core-100.0.3.dist-info/RECORD
