Metadata-Version: 2.3
Name: swit-core
Version: 100.0.3
Summary: this is a switbuilder core package
Project-URL: Homepage, https://github.com/pypa/sampleproject
Project-URL: Bug Tracker, https://github.com/pypa/sampleproject/issues
Author-email: ur-team <developers@swit.io>
Classifier: License :: OSI Approved :: MIT License
Classifier: Operating System :: OS Independent
Classifier: Programming Language :: Python :: 3
Requires-Python: >=3.10
Requires-Dist: fastapi~=0.109.2
Requires-Dist: httpx>=0.26.0
Requires-Dist: pyjwt==2.8.0
Requires-Dist: pymysql>=1.1.0
Requires-Dist: python-dotenv>=1.0.1
Requires-Dist: sqlalchemy>=2.0.27
Requires-Dist: ur-tunnel>=0.0.13
Requires-Dist: uvicorn>=0.27.1
